vgram.cpython-37m-darwin.so
binding/__init__.py
binding/src/__init__.py
binding/src/test/__init__.py
vgram-0.4.2.dist-info/LICENSE
vgram-0.4.2.dist-info/METADATA
vgram-0.4.2.dist-info/WHEEL
vgram-0.4.2.dist-info/top_level.txt
vgram-0.4.2.dist-info/RECORD
