Metadata-Version: 2.1
Name: vgram
Version: 0.4.2
Summary: V-gram builder library
Home-page: https://github.com/akhvorov/vgram
Author: Aleksandr Khvorov
Author-email: khvorov.aleksandr@gmail.com
License: UNKNOWN
Platform: UNKNOWN
Requires-Dist: numpy
Requires-Dist: scikit-learn
